RotL/__init__.py
RotL/windows.py
RotL/templates/windows_remediation_template.ini
RotL-0.0.5.dist-info/LICENSE
RotL-0.0.5.dist-info/METADATA
RotL-0.0.5.dist-info/WHEEL
RotL-0.0.5.dist-info/entry_points.txt
RotL-0.0.5.dist-info/top_level.txt
RotL-0.0.5.dist-info/RECORD
