Metadata-Version: 2.1
Name: RotL
Version: 0.0.5
Summary: A simple utility for converting files that describe malware infections into remediation scripts that can clean up infections using native OS tools.
Home-page: https://github.com/IntegralDefense/RotL
Author: Sean McFeely
Author-email: zsmcfeely@gmail.com
License: Apache-2.0
Keywords: Incident Response,Remediation,Malware
Platform: UNKNOWN
Classifier: Development Status :: 4 - Beta
Classifier: Intended Audience :: Developers
Classifier: Intended Audience :: Information Technology
Classifier: Intended Audience :: Telecommunications Industry
Classifier: Operating System :: OS Independent
Classifier: License :: OSI Approved :: Apache Software License
Classifier: Programming Language :: Python :: 3 :: Only
Classifier: Programming Language :: Python :: 3
Classifier: Programming Language :: Python :: 3.0
Classifier: Programming Language :: Python :: 3.1
Classifier: Programming Language :: Python :: 3.2
Classifier: Programming Language :: Python :: 3.3
Classifier: Programming Language :: Python :: 3.4
Classifier: Programming Language :: Python :: 3.5
Classifier: Programming Language :: Python :: 3.6
